{
  "annotations": { "list": [] },
  "editable": true,
  "fiscalYearStartMonth": 0,
  "graphTooltip": 0,
  "id": null,
  "links": [],
  "panels": [
    {
      "datasource": { "type": "loki", "uid": "loki" },
      "gridPos": { "h": 4, "w": 24, "x": 0, "y": 0 },
      "id": 1,
      "options": {
        "dedupStrategy": "none",
        "enableLogDetails": true,
        "prettifyLogMessage": false,
        "showCommonLabels": false,
        "showLabels": true,
        "showTime": true,
        "sortOrder": "Descending",
        "wrapLogMessage": true
      },
      "targets": [
        {
          "datasource": { "type": "loki", "uid": "loki" },
          "expr": "{job=\"syslog\"} |= \"$search\"",
          "refId": "A"
        }
      ],
      "title": "Alle Syslog-Einträge",
      "type": "logs"
    },
    {
      "datasource": { "type": "loki", "uid": "loki" },
      "gridPos": { "h": 4, "w": 12, "x": 0, "y": 4 },
      "id": 2,
      "options": {
        "dedupStrategy": "none",
        "enableLogDetails": true,
        "showLabels": true,
        "showTime": true,
        "sortOrder": "Descending",
        "wrapLogMessage": true
      },
      "targets": [
        {
          "datasource": { "type": "loki", "uid": "loki" },
          "expr": "{job=\"syslog\", host=~\"$host\"}",
          "refId": "A"
        }
      ],
      "title": "Logs pro Host",
      "type": "logs"
    },
    {
      "datasource": { "type": "loki", "uid": "loki" },
      "fieldConfig": {
        "defaults": {
          "color": { "mode": "palette-classic" },
          "custom": {
            "axisBorderShow": false,
            "drawStyle": "bars",
            "fillOpacity": 80,
            "stacking": { "mode": "normal" }
          },
          "unit": "short"
        },
        "overrides": []
      },
      "gridPos": { "h": 4, "w": 12, "x": 12, "y": 4 },
      "id": 3,
      "targets": [
        {
          "datasource": { "type": "loki", "uid": "loki" },
          "expr": "sum by (host) (count_over_time({job=\"syslog\"}[5m]))",
          "legendFormat": "{{host}}",
          "refId": "A"
        }
      ],
      "title": "Log-Volumen pro Host (5m)",
      "type": "timeseries"
    }
  ],
  "refresh": "30s",
  "schemaVersion": 39,
  "tags": ["ops", "syslog", "loki"],
  "templating": {
    "list": [
      {
        "current": { "selected": false, "text": "All", "value": "$__all" },
        "datasource": { "type": "loki", "uid": "loki" },
        "definition": "label_values({job=\"syslog\"}, host)",
        "includeAll": true,
        "label": "Host",
        "multi": true,
        "name": "host",
        "query": "label_values({job=\"syslog\"}, host)",
        "refresh": 2,
        "type": "query"
      },
      {
        "current": { "selected": false, "text": "", "value": "" },
        "label": "Suche",
        "name": "search",
        "options": [{ "selected": true, "text": "", "value": "" }],
        "query": "",
        "type": "textbox"
      }
    ]
  },
  "time": { "from": "now-1h", "to": "now" },
  "timepicker": {},
  "timezone": "browser",
  "title": "HVM Syslog Analyse",
  "uid": "hvm-syslog-analysis",
  "version": 1
}
